sbc_drf_authtoken/__init__.py
sbc_drf_authtoken/apps.py
sbc_drf_authtoken/errors.py
sbc_drf_authtoken/permissions.py
sbc_drf_authtoken/serializers.py
sbc_drf_authtoken/signals.py
sbc_drf_authtoken/tests.py
sbc_drf_authtoken/urls.py
sbc_drf_authtoken/views.py
sbc_drf_authtoken/migrations/__init__.py
sbc_drf_authtoken-1.1.2.dist-info/LICENSE
sbc_drf_authtoken-1.1.2.dist-info/METADATA
sbc_drf_authtoken-1.1.2.dist-info/WHEEL
sbc_drf_authtoken-1.1.2.dist-info/top_level.txt
sbc_drf_authtoken-1.1.2.dist-info/zip-safe
sbc_drf_authtoken-1.1.2.dist-info/RECORD
