Metadata-Version: 2.1
Name: sbc-drf-authtoken
Version: 1.1.2
Summary: Token-based authentication API app for DRF.
Home-page: https://gitlab.stickboycreative.com/sbc-python/sbc_drf_authtoken
Author: Abhinav Kotak
Author-email: in.abhi9@gmail.com
Maintainer: Abhinav Kotak
Maintainer-email: in.abhi9@gmail.com
License: MIT License
Requires-Dist: six
Requires-Dist: wheel
Requires-Dist: django (<=3.2,>=3.0)
Requires-Dist: djangorestframework (<4.0,>=3.11)
